content_access_control/__init__.py
content_access_control/adapter.py
content_access_control/admin.py
content_access_control/admin_permission.py
content_access_control/apps.py
content_access_control/backend.py
content_access_control/core.py
content_access_control/enforcer.py
content_access_control/middleware.py
content_access_control/model_identifiers.py
content_access_control/models.py
content_access_control/permissions.py
content_access_control/policy_mixins.py
content_access_control/utils.py
content_access_control/migrations/0001_initial.py
content_access_control/migrations/__init__.py
django_content_access_control-0.3.0.dist-info/licenses/LICENSE
django_content_access_control-0.3.0.dist-info/METADATA
django_content_access_control-0.3.0.dist-info/WHEEL
django_content_access_control-0.3.0.dist-info/top_level.txt
django_content_access_control-0.3.0.dist-info/RECORD
