Metadata-Version: 2.4
Name: django-content-access-control
Version: 0.3.0
Requires-Python: >=3.10
License-File: LICENSE
Requires-Dist: casbin>=1.43.0
Requires-Dist: django>=4.2
Requires-Dist: pycasbin>=2.2.0
Dynamic: license-file
